metnet3_pytorch/__init__.py
metnet3_pytorch/metnet3_pytorch.py
metnet3_pytorch-0.0.12.dist-info/LICENSE
metnet3_pytorch-0.0.12.dist-info/METADATA
metnet3_pytorch-0.0.12.dist-info/WHEEL
metnet3_pytorch-0.0.12.dist-info/top_level.txt
metnet3_pytorch-0.0.12.dist-info/RECORD
