Metadata-Version: 2.1
Name: metnet3-pytorch
Version: 0.0.12
Summary: MetNet 3 - Pytorch
Home-page: https://github.com/lucidrains/metnet3-pytorch
Author: Phil Wang
Author-email: lucidrains@gmail.com
License: MIT
Keywords: artificial intelligence,deep learning,vision transformers,unet,weather forecasting
Classifier: Development Status :: 4 - Beta
Classifier: Intended Audience :: Developers
Classifier: Topic :: Scientific/Engineering :: Artificial Intelligence
Classifier: License :: OSI Approved :: MIT License
Classifier: Programming Language :: Python :: 3.6
License-File: LICENSE
Requires-Dist: beartype
Requires-Dist: einops >=0.7.0
Requires-Dist: torch >=2.0
